oauthkit_google/__init__.py
oauthkit_google/__main__.py
oauthkit_google/cli.py
oauthkit_google/interfaces.py
oauthkit_google/proxy.py
oauthkit_google/locale/en/LC_MESSAGES/oauthkit-google.mo
oauthkit_google/locale/ko/LC_MESSAGES/oauthkit-google.mo
oauthkit_google-0.1.2.dist-info/METADATA
oauthkit_google-0.1.2.dist-info/RECORD
oauthkit_google-0.1.2.dist-info/WHEEL
oauthkit_google-0.1.2.dist-info/entry_points.txt
oauthkit_google-0.1.2.dist-info/top_level.txt
