Metadata-Version: 2.1
Name: oauthkit-google
Version: 0.1.2
Summary: OAuthKit for Google
Home-page: https://github.com/mete0r/oauthkit-google
Author: mete0r
Author-email: mete0r@sarangbang.or.kr
License: GNU Lesser General Public License v3 or later (LGPLv3+)
Keywords: oauth,google
Platform: UNKNOWN
Classifier: Development Status :: 1 - Planning
Classifier: Intended Audience :: Developers
Classifier: License :: OSI Approved :: GNU Lesser General Public License v3 or later (LGPLv3+)
Classifier: Operating System :: OS Independent
Classifier: Programming Language :: Python
Classifier: Programming Language :: Python :: 2.7
Classifier: Programming Language :: Python :: 3.4
Classifier: Programming Language :: Python :: Implementation :: CPython
Provides-Extra: test
Requires-Dist: jsonable-objects (>=0.1.4)
Requires-Dist: zope.interface
Provides-Extra: test
Requires-Dist: coverage (>=4.5.1); extra == 'test'
Requires-Dist: pytest (>=3.9.2); extra == 'test'
